badi_utils/__init__.py
badi_utils/date_calc.py
badi_utils/dynamic.py
badi_utils/dynamic_api.py
badi_utils/dynamic_models.py
badi_utils/email.py
badi_utils/errors.py
badi_utils/logging.py
badi_utils/responses.py
badi_utils/rss.py
badi_utils/select2.py
badi_utils/sms.py
badi_utils/utils.py
badi_utils/validations.py
badi_utils/static/badi_utils/css/custom.css
badi_utils/static/badi_utils/css/fonts/IRANSansWeb(FaNum).eot
badi_utils/static/badi_utils/css/fonts/IRANSansWeb(FaNum).ttf
badi_utils/static/badi_utils/css/fonts/IRANSansWeb(FaNum).woff
badi_utils/static/badi_utils/css/fonts/IRANSansWeb(FaNum).woff2
badi_utils/static/badi_utils/css/fonts/IRANSansWeb(FaNum)_2.eot
badi_utils/static/badi_utils/css/fonts/IRANSansWeb(FaNum)_Bold.eot
badi_utils/static/badi_utils/css/fonts/IRANSansWeb(FaNum)_Bold.ttf
badi_utils/static/badi_utils/css/fonts/IRANSansWeb(FaNum)_Bold.woff
badi_utils/static/badi_utils/css/fonts/IRANSansWeb(FaNum)_Bold.woff2
badi_utils/static/badi_utils/css/fonts/IRANSansWeb(FaNum)_Bold_2.eot
badi_utils/static/badi_utils/css/fonts/IRANSansWeb(FaNum)_Light.eot
badi_utils/static/badi_utils/css/fonts/IRANSansWeb(FaNum)_Light.ttf
badi_utils/static/badi_utils/css/fonts/IRANSansWeb(FaNum)_Light.woff
badi_utils/static/badi_utils/css/fonts/IRANSansWeb(FaNum)_Light.woff2
badi_utils/static/badi_utils/css/fonts/IRANSansWeb(FaNum)_Light_2.eot
badi_utils/static/badi_utils/css/fonts/IRANSansWeb(FaNum)_Medium.eot
badi_utils/static/badi_utils/css/fonts/IRANSansWeb(FaNum)_Medium.ttf
badi_utils/static/badi_utils/css/fonts/IRANSansWeb(FaNum)_Medium.woff
badi_utils/static/badi_utils/css/fonts/IRANSansWeb(FaNum)_Medium.woff2
badi_utils/static/badi_utils/css/fonts/IRANSansWeb(FaNum)_Medium_2.eot
badi_utils/static/badi_utils/css/fonts/IRANSansWeb(FaNum)_UltraLight.eot
badi_utils/static/badi_utils/css/fonts/IRANSansWeb(FaNum)_UltraLight.ttf
badi_utils/static/badi_utils/css/fonts/IRANSansWeb(FaNum)_UltraLight.woff
badi_utils-1.1.5.dist-info/METADATA
badi_utils-1.1.5.dist-info/WHEEL
badi_utils-1.1.5.dist-info/licenses/LICENSE
badi_utils-1.1.5.dist-info/RECORD
